{
    "filename": "blog_creation_tasks.md",
    "nome": "Tarefas de Criação de Blog",
    "url": "https://github.com/srbentostk/prompts/blob/main/arquivos_traduzidos/blog_creation_tasks.md",
    "descricao": "O arquivo contém um conjunto de diretrizes e tarefas para ajudar na criação de um blog de sucesso. Ele aborda a geração de ideias de conteúdo, sugestões de SEO e orientações sobre como escrever postagens de blog envolventes. O objetivo é fornecer uma estrutura organizada e prática para otimizar a criação e o desempenho das postagens, garantindo engajamento e relevância para o público-alvo.",
    "tags": [
        "Criação de Conteúdo",
        "SEO",
        "Blog"
    ]
}