{
    "filename": "create_video_presentation_plan.md",
    "nome": "Criar Plano de Apresentação em Vídeo",
    "url": "https://github.com/srbentostk/prompts/blob/main/arquivos_traduzidos/create_video_presentation_plan.md",
    "descricao": "Este arquivo orienta a criação de um plano de apresentação em vídeo para a empresa World Seas Shipping Bahrain, com foco em publicidade nas redes sociais. O objetivo é destacar a marca e os serviços da empresa, identificando o público-alvo, definindo a mensagem principal, sugerindo elementos visuais e de áudio, elaborando chamadas para ação e propondo métricas de sucesso. O plano deve ser estrutur",
    "tags": [
        "Criação de Conteúdo",
        "Marketing",
        "Redes Sociais"
    ]
}