{
    "filename": "engaging_writing_prompts.md",
    "nome": "Prompts de Escrita Envolventes",
    "url": "https://github.com/srbentostk/prompts/blob/main/arquivos_traduzidos/engaging_writing_prompts.md",
    "descricao": "O objetivo deste prompt é ajudar professores e autores a criar prompts de escrita envolventes e adequados para alunos do ensino fundamental e médio, além de sugerir maneiras de incorporar ilustrações e desenhar capas de livros. O arquivo solicita ideias específicas para diferentes faixas etárias e gêneros literários, visando aprimorar a criatividade e o aprendizado dos estudantes.",
    "tags": [
        "Criação de Conteúdo",
        "Ensino",
        "Escrita"
    ]
}