{
    "filename": "mathematics_lesson_plan.md",
    "nome": "Plano de Aula de Matemática",
    "url": "https://github.com/srbentostk/prompts/blob/main/arquivos_traduzidos/mathematics_lesson_plan.md",
    "descricao": "O arquivo contém diretrizes para a criação de um plano de aula de matemática para nível escolar, abordando conceitos fundamentais como operações aritméticas, frações, decimais, porcentagens, geometria e álgebra introdutória. O plano deve incluir objetivos de aprendizagem, métodos de ensino variados, estratégias de engajamento e diferenciação para atender às diversas necessidades dos alunos.",
    "tags": [
        "Ensino",
        "Educação",
        "Matemática"
    ]
}