{
    "filename": "plan_perfect_honeymoon.md",
    "nome": "Planejar Lua de Mel Perfeita",
    "url": "https://github.com/srbentostk/prompts/blob/main/arquivos_traduzidos/plan_perfect_honeymoon.md",
    "descricao": "O arquivo contém um prompt que orienta a criação de um planejamento detalhado para uma lua de mel perfeita, incluindo recomendações de destinos românticos, experiências culinárias, opções de hospedagem, transporte, dicas de comunicação e atividades românticas. O objetivo é garantir que a experiência da lua de mel seja memorável e especial.",
    "tags": [
        "Viagem",
        "Criação de Conteúdo",
        "Planejamento de Eventos"
    ]
}