{
    "filename": "survey_design_framework.md",
    "nome": "Estrutura de Design de Pesquisa",
    "url": "https://github.com/srbentostk/prompts/blob/main/arquivos_traduzidos/survey_design_framework.md",
    "descricao": "Este documento orienta na criação de um estudo de pesquisa por survey, abordando categorias essenciais como hábitos e usos, conscientização, imagem da marca e trabalho de segmentação. Para cada categoria, são sugeridos elementos como definição de perguntas, métodos de análise de dados e estratégias de interpretação, visando coletar insights profundos sobre o público e a percepção da marca.",
    "tags": [
        "Pesquisa",
        "Marketing",
        "Análise de Dados"
    ]
}