{
    "filename": "thanksgiving_coloring_book_outline.md",
    "nome": "Esboço do Livro de Colorir de Ação de Graças",
    "url": "https://github.com/srbentostk/prompts/blob/main/arquivos_traduzidos/thanksgiving_coloring_book_outline.md",
    "descricao": "O prompt solicita a criação de um esboço detalhado para um livro de colorir com tema de Ação de Graças, abrangendo 48 páginas. Inclui diretrizes sobre tema, conteúdo, complexidade das ilustrações, organização das páginas e sugestões de atividades adicionais para uma experiência enriquecedora.",
    "tags": [
        "Criação de Conteúdo",
        "Escrita Criativa",
        "Projetos Criativos"
    ]
}